LICENSE.txt
MANIFEST.in
README.md
setup.py
doc/.nojekyll
doc/CNAME
doc/Makefile
doc/_site.yml
doc/index.md
doc/search.md
doc/start.md
doc/_layouts/_base.html
doc/_layouts/analytics.html
doc/_layouts/footer.html
doc/_layouts/home.html
doc/_layouts/index.html
doc/_layouts/newsfeed.html
doc/_layouts/page.html
doc/_layouts/search.html
doc/_layouts/sharing.html
doc/_layouts/simple_page.html
doc/_layouts/util.html
doc/_python/__init__.py
doc/_python/filters.py
doc/_python/hooks.py
doc/css/bootstrap.css
doc/css/bootstrap.min.css
doc/css/site.css
doc/css/syntax.css
doc/faq/baseurl-preview.md
doc/faq/formulas.md
doc/faq/index.md
doc/faq/licensing-requirements.md
doc/faq/link2section.md
doc/faq/media-files.md
doc/faq/sitemap.md
doc/faq/tags.md
doc/img/urubu.jpg
doc/img/urubu_cover.png
doc/js/bootstrap.js
doc/js/bootstrap.min.js
doc/manual/authoring.md
doc/manual/building.md
doc/manual/extensions.md
doc/manual/hooks.md
doc/manual/index.md
doc/manual/install.md
doc/manual/intro.md
doc/manual/search.md
doc/manual/structure.md
doc/manual/templates.md
doc/manual/templating-in-pages.md
doc/more/about.md
doc/more/index.md
doc/more/sites.md
doc/news/2014-01-12.md
doc/news/2014-01-22.md
doc/news/2014-02-15.md
doc/news/2014-02-27.md
doc/news/2014-03-18.md
doc/news/2014-05-25.md
doc/news/2014-09-08.md
doc/news/2015-01-28.md
doc/news/2015-03-07.md
doc/news/2015-11-22.md
doc/news/2015-12-15.md
doc/news/2016-01-01.md
doc/news/2016-01-10.md
doc/news/2016-02-12.md
doc/news/2016-11-14.md
doc/news/index.md
doc/tipuesearch/tipuesearch.css
doc/tipuesearch/tipuesearch.css.in
doc/tipuesearch/tipuesearch.js
doc/tipuesearch/tipuesearch.min.js
doc/tipuesearch/tipuesearch_content.js
doc/tipuesearch/tipuesearch_set.js
doc/tipuesearch/img/.DS_Store
doc/tipuesearch/img/search.png
urubu/__init__.py
urubu/__main__.py
urubu/_compat.py
urubu/config.py
urubu/httphandler.py
urubu/main.py
urubu/md_extensions.py
urubu/processors.py
urubu/project.py
urubu/readers.py
urubu.egg-info/PKG-INFO
urubu.egg-info/SOURCES.txt
urubu.egg-info/dependency_links.txt
urubu.egg-info/entry_points.txt
urubu.egg-info/requires.txt
urubu.egg-info/top_level.txt