Metadata-Version: 1.1
Name: urubu
Version: 1.3.0
Summary: A micro CMS for static websites with a focus on good navigation practices.
Home-page: http://urubu.jandecaluwe.com
Author: Jan Decaluwe
Author-email: jan@jandecaluwe.com
License: UNKNOWN
Platform: UNKNOWN
Classifier: Development Status :: 3 - Alpha
Classifier: License :: OSI Approved :: GNU Affero General Public License v3
Classifier: Operating System :: OS Independent
Classifier: Programming Language :: Python :: 2.7
Classifier: Topic :: Internet :: WWW/HTTP
Classifier: Topic :: Software Development :: Libraries :: Python Modules
